pyqed/FranckCondon.py
pyqed/__init__.py
pyqed/backup.py
pyqed/beam.py
pyqed/cavity.py
pyqed/common.py
pyqed/coordinates.py
pyqed/correlation.py
pyqed/fft.py
pyqed/group.py
pyqed/gwp.py
pyqed/igner.py
pyqed/liouville.py
pyqed/mol.py
pyqed/noise.py
pyqed/optics.py
pyqed/oqs.py
pyqed/pd.py
pyqed/phys.py
pyqed/qnm.py
pyqed/quadrature.py
pyqed/spin_boson.py
pyqed/style.py
pyqed/superoperator.py
pyqed/susceptibility.py
pyqed/units.py
pyqed/wigner.py
pyqed/wpd.py
pyqed/Floquet/Floquet.py
pyqed/Floquet/FloquetBloch.py
pyqed/Floquet/__init__.py
pyqed/Floquet/free_electron.py
pyqed/beam/__init__.py
pyqed/beam/config.py
pyqed/beam/scalar_fields_X.py
pyqed/beam/scalar_fields_XY.py
pyqed/beam/scalar_fields_XYZ.py
pyqed/beam/scalar_fields_XZ.py
pyqed/beam/scalar_fields_Z.py
pyqed/beam/scalar_masks_X.py
pyqed/beam/scalar_masks_XY.py
pyqed/beam/scalar_masks_XYZ.py
pyqed/beam/scalar_masks_XZ.py
pyqed/beam/scalar_sources_X.py
pyqed/beam/scalar_sources_XY.py
pyqed/beam/utils_common.py
pyqed/beam/utils_drawing.py
pyqed/beam/utils_math.py
pyqed/beam/utils_multiprocessing.py
pyqed/beam/utils_optics.py
pyqed/beam/utils_slicer.py
pyqed/beam/utils_tests.py
pyqed/beam/vector_fields_XY.py
pyqed/beam/vector_masks_XY.py
pyqed/beam/vector_sources_XY.py
pyqed/dvr/__init__.py
pyqed/dvr/dvr.py
pyqed/dvr/dvr_1d.py
pyqed/dvr/dvr_2d.py
pyqed/dvr/gauss_hermite.py
pyqed/models/__init__.py
pyqed/models/dho.py
pyqed/models/jahn_teller.py
pyqed/models/pyrazine.py
pyqed/models/pyrrole.py
pyqed/polariton/__init__.py
pyqed/polariton/cavity.py
pyqed/qchem/FCI.py
pyqed/qchem/HF.py
pyqed/qchem/core.py
pyqed/qchem/current_density.py
pyqed/qchem/density.py
pyqed/qchem/dyson.py
pyqed/qchem/plt.py
pyqed/qchem/tdhf.py
pyqed/qchem/view.py
pyqed/signal/2DES.py
pyqed/signal/ETPA.py
pyqed/signal/__init__.py
pyqed/signal/liouville.py
pyqed/signal/nonhermitian.py
pyqed/signal/sos.py
qed/__init__.py
pyqed-0.1.5.dist-info/LICENSE
pyqed-0.1.5.dist-info/METADATA
pyqed-0.1.5.dist-info/WHEEL
pyqed-0.1.5.dist-info/entry_points.txt
pyqed-0.1.5.dist-info/top_level.txt
pyqed-0.1.5.dist-info/RECORD
