Metadata-Version: 2.1
Name: pyqed
Version: 0.1.5
Summary: ultrafast spectroscopy, cavity quantum electrodynamics
Home-page: https://github.com/binggu56/pyqed
Author: Bing Gu
Author-email: binggu56@gmail.com
License: MIT license
Keywords: pyqed
Platform: UNKNOWN
Classifier: Development Status :: 2 - Pre-Alpha
Classifier: Intended Audience :: Developers
Classifier: License :: OSI Approved :: MIT License
Classifier: Natural Language :: English
Classifier: Programming Language :: Python :: 2
Classifier: Programming Language :: Python :: 2.7
Classifier: Programming Language :: Python :: 3
Classifier: Programming Language :: Python :: 3.4
Classifier: Programming Language :: Python :: 3.5
Classifier: Programming Language :: Python :: 3.6
Classifier: Programming Language :: Python :: 3.7
Requires-Dist: Click (>=6.0)
Requires-Dist: numpy
Requires-Dist: scipy
